Metadata-Version: 2.1
Name: microbench
Version: 0.9.1
Summary: Micro-benchmarking framework. Extensible, with distributed/cluster support.
Home-page: https://github.com/alubbock/microbench
Author: Alex Lubbock
Author-email: code@alexlubbock.com
License: UNKNOWN
Platform: UNKNOWN
Classifier: Intended Audience :: Developers
Classifier: Intended Audience :: Science/Research
Classifier: License :: OSI Approved :: MIT License
Classifier: Programming Language :: Python
License-File: LICENSE
